dbt_docs_publisher/__init__.py
dbt_docs_publisher/cli.py
dbt_docs_publisher/uploader.py
tests/__init__.py
tests/test_cli.py
dbt_docs_publisher-0.1.0.dist-info/LICENSE
dbt_docs_publisher-0.1.0.dist-info/METADATA
dbt_docs_publisher-0.1.0.dist-info/WHEEL
dbt_docs_publisher-0.1.0.dist-info/entry_points.txt
dbt_docs_publisher-0.1.0.dist-info/top_level.txt
dbt_docs_publisher-0.1.0.dist-info/RECORD
