Metadata-Version: 2.1
Name: dbt-docs-publisher
Version: 0.1.0
Summary: A CLI tool for publishing dbt docs to Azure Blob Storage
Home-page: https://github.com/yourusername/dbt-docs-publisher
Author: 
Author-email: 
Classifier: Development Status :: 3 - Alpha
Classifier: Intended Audience :: Developers
Classifier: Intended Audience :: Information Technology
Classifier: License :: OSI Approved :: MIT License
Classifier: Programming Language :: Python :: 3
Classifier: Programming Language :: Python :: 3.7
Classifier: Programming Language :: Python :: 3.8
Classifier: Programming Language :: Python :: 3.9
Classifier: Programming Language :: Python :: 3.10
Classifier: Programming Language :: Python :: 3.11
Requires-Python: >=3.7
License-File: LICENSE
Requires-Dist: azure-storage-blob >=12.0.0
Provides-Extra: databricks
Requires-Dist: dbt-databricks >=1.0.0 ; extra == 'databricks'
Provides-Extra: dev
Requires-Dist: pytest >=6.0 ; extra == 'dev'
Requires-Dist: black >=20.8b1 ; extra == 'dev'
Requires-Dist: flake8 >=3.8.0 ; extra == 'dev'
Requires-Dist: twine >=3.4.0 ; extra == 'dev'
